{
  "id": "human-nicknames",
  "game": { "collection": "games", "id": "x5" },
  "category": "design",
  "title": "Los ocho Mavericks tienen apodos humanos ocultos",
  "body": "Además de sus nombres oficiales (Crescent Grizzly, Tidal Whale, etc.), Mega Man X5 le da a cada uno de los ocho Mavericks un apodo con sonoridad humana que aparece en los créditos y en material gráfico del juego: Grizzly Slash, Duff McWhalen, Squid Adler, Izzy Glow, Dark Dizzy, The Skiver, Mattrex y Axle the Red. Es una particularidad única de esta entrega dentro de la serie principal.",
  "sourceUrl": "https://megaman.fandom.com/wiki/Mega_Man_X5"
}
